{
    "cod": "200",
    "message": 0,
    "cnt": 40,
    "list": [
        {
            "dt": 1701097200,
            "main": {
                "temp": 278.8,
                "feels_like": 275.21,
                "temp_min": 278.8,
                "temp_max": 279.53,
                "pressure": 1002,
                "sea_level": 1002,
                "grnd_level": 1000,
                "humidity": 88,
                "temp_kf": -0.73
            },
            "weather": [
                {
                    "id": 500,
                    "main": "Rain",
                    "description": "light rain",
                    "icon": "10d"
                }
            ],
            "clouds": {
                "all": 83
            },
            "wind": {
                "speed": 5.2,
                "deg": 340,
                "gust": 9.16
            },
            "visibility": 10000,
            "pop": 0.4,
            "rain": {
                "3h": 0.19
            },
            "sys": {
                "pod": "d"
            },
            "dt_txt": "2023-11-27 15:00:00"
        },
        {
            "dt": 1701108000,
            "main": {
                "temp": 279.01,
                "feels_like": 275.41,
                "temp_min": 279.01,
                "temp_max": 279.29,
                "pressure": 1004,
                "sea_level": 1004,
                "grnd_level": 1002,
                "humidity": 85,
                "temp_kf": -0.28
            },
            "weather": [
                {
                    "id": 803,
                    "main": "Clouds",
                    "description": "broken clouds",
                    "icon": "04n"
                }
            ],
            "clouds": {
                "all": 80
            },
            "wind": {
                "speed": 5.35,
                "deg": 353,
                "gust": 9.94
            },
            "visibility": 10000,
            "pop": 0.21,
            "sys": {
                "pod": "n"
            },
            "dt_txt": "2023-11-27 18:00:00"
        },
        {
            "dt": 1701118800,
            "main": {
                "temp": 279.32,
                "feels_like": 276.25,
                "temp_min": 279.32,
                "temp_max": 279.32,
                "pressure": 1007,
                "sea_level": 1007,
                "grnd_level": 1004,
                "humidity": 83,
                "temp_kf": 0
            },
            "weather": [
                {
                    "id": 804,
                    "main": "Clouds",
                    "description": "overcast clouds",
                    "icon": "04n"
                }
            ],
            "clouds": {
                "all": 91
            },
            "wind": {
                "speed": 4.37,
                "deg": 354,
                "gust": 8.72
            },
            "visibility": 10000,
            "pop": 0,
            "sys": {
                "pod": "n"
            },
            "dt_txt": "2023-11-27 21:00:00"
        },
        {
            "dt": 1701129600,
            "main": {
                "temp": 279.13,
                "feels_like": 275.93,
                "temp_min": 279.13,
                "temp_max": 279.13,
                "pressure": 1009,
                "sea_level": 1009,
                "grnd_level": 1006,
                "humidity": 81,
                "temp_kf": 0
            },
            "weather": [
                {
                    "id": 803,
                    "main": "Clouds",
                    "description": "broken clouds",
                    "icon": "04n"
                }
            ],
            "clouds": {
                "all": 75
            },
            "wind": {
                "speed": 4.55,
                "deg": 25,
                "gust": 9.06
            },
            "visibility": 10000,
            "pop": 0,
            "sys": {
                "pod": "n"
            },
            "dt_txt": "2023-11-28 00:00:00"
        },
        {
            "dt": 1701140400,
            "main": {
                "temp": 278.73,
                "feels_like": 276.7,
                "temp_min": 278.73,
                "temp_max": 278.73,
                "pressure": 1012,
                "sea_level": 1012,
                "grnd_level": 1008,
                "humidity": 83,
                "temp_kf": 0
            },
            "weather": [
                {
                    "id": 804,
                    "main": "Clouds",
                    "description": "overcast clouds",
                    "icon": "04n"
                }
            ],
            "clouds": {
                "all": 98
            },
            "wind": {
                "speed": 2.54,
                "deg": 28,
                "gust": 5.06
            },
            "visibility": 10000,
            "pop": 0,
            "sys": {
                "pod": "n"
            },
            "dt_txt": "2023-11-28 03:00:00"
        },
        {
            "dt": 1701151200,
            "main": {
                "temp": 277.28,
                "feels_like": 274.92,
                "temp_min": 277.28,
                "temp_max": 277.28,
                "pressure": 1013,
                "sea_level": 1013,
                "grnd_level": 1009,
                "humidity": 86,
                "temp_kf": 0
            },
            "weather": [
                {
                    "id": 804,
                    "main": "Clouds",
                    "description": "overcast clouds",
                    "icon": "04n"
                }
            ],
            "clouds": {
                "all": 92
            },
            "wind": {
                "speed": 2.62,
                "deg": 36,
                "gust": 4.4
            },
            "visibility": 10000,
            "pop": 0.01,
            "sys": {
                "pod": "n"
            },
            "dt_txt": "2023-11-28 06:00:00"
        },
        {
            "dt": 1701162000,
            "main": {
                "temp": 277.05,
                "feels_like": 277.05,
                "temp_min": 277.05,
                "temp_max": 277.05,
                "pressure": 1014,
                "sea_level": 1014,
                "grnd_level": 1010,
                "humidity": 83,
                "temp_kf": 0
            },
            "weather": [
                {
                    "id": 803,
                    "main": "Clouds",
                    "description": "broken clouds",
                    "icon": "04d"
                }
            ],
            "clouds": {
                "all": 58
            },
            "wind": {
                "speed": 1.3,
                "deg": 72,
                "gust": 1.76
            },
            "visibility": 10000,
            "pop": 0,
            "sys": {
                "pod": "d"
            },
            "dt_txt": "2023-11-28 09:00:00"
        },
        {
            "dt": 1701172800,
            "main": {
                "temp": 278.85,
                "feels_like": 278.85,
                "temp_min": 278.85,
                "temp_max": 278.85,
                "pressure": 1013,
                "sea_level": 1013,
                "grnd_level": 1010,
                "humidity": 71,
                "temp_kf": 0
            },
            "weather": [
                {
                    "id": 802,
                    "main": "Clouds",
                    "description": "scattered clouds",
                    "icon": "03d"
                }
            ],
            "clouds": {
                "all": 39
            },
            "wind": {
                "speed": 1.15,
                "deg": 197,
                "gust": 1.55
            },
            "visibility": 10000,
            "pop": 0,
            "sys": {
                "pod": "d"
            },
            "dt_txt": "2023-11-28 12:00:00"
        },
        {
            "dt": 1701183600,
            "main": {
                "temp": 278.77,
                "feels_like": 278.77,
                "temp_min": 278.77,
                "temp_max": 278.77,
                "pressure": 1012,
                "sea_level": 1012,
                "grnd_level": 1009,
                "humidity": 73,
                "temp_kf": 0
            },
            "weather": [
                {
                    "id": 801,
                    "main": "Clouds",
                    "description": "few clouds",
                    "icon": "02d"
                }
            ],
            "clouds": {
                "all": 12
            },
            "wind": {
                "speed": 0.68,
                "deg": 242,
                "gust": 0.99
            },
            "visibility": 10000,
            "pop": 0,
            "sys": {
                "pod": "d"
            },
            "dt_txt": "2023-11-28 15:00:00"
        },
        {
            "dt": 1701194400,
            "main": {
                "temp": 277.83,
                "feels_like": 276.94,
                "temp_min": 277.83,
                "temp_max": 277.83,
                "pressure": 1011,
                "sea_level": 1011,
                "grnd_level": 1008,
                "humidity": 77,
                "temp_kf": 0
            },
            "weather": [
                {
                    "id": 802,
                    "main": "Clouds",
                    "description": "scattered clouds",
                    "icon": "03n"
                }
            ],
            "clouds": {
                "all": 31
            },
            "wind": {
                "speed": 1.35,
                "deg": 162,
                "gust": 1.46
            },
            "visibility": 10000,
            "pop": 0,
            "sys": {
                "pod": "n"
            },
            "dt_txt": "2023-11-28 18:00:00"
        },
        {
            "dt": 1701205200,
            "main": {
                "temp": 277.4,
                "feels_like": 274.09,
                "temp_min": 277.4,
                "temp_max": 277.4,
                "pressure": 1010,
                "sea_level": 1010,
                "grnd_level": 1007,
                "humidity": 84,
                "temp_kf": 0
            },
            "weather": [
                {
                    "id": 803,
                    "main": "Clouds",
                    "description": "broken clouds",
                    "icon": "04n"
                }
            ],
            "clouds": {
                "all": 58
            },
            "wind": {
                "speed": 4,
                "deg": 249,
                "gust": 6.27
            },
            "visibility": 10000,
            "pop": 0.2,
            "sys": {
                "pod": "n"
            },
            "dt_txt": "2023-11-28 21:00:00"
        },
        {
            "dt": 1701216000,
            "main": {
                "temp": 278.4,
                "feels_like": 275.88,
                "temp_min": 278.4,
                "temp_max": 278.4,
                "pressure": 1008,
                "sea_level": 1008,
                "grnd_level": 1005,
                "humidity": 89,
                "temp_kf": 0
            },
            "weather": [
                {
                    "id": 500,
                    "main": "Rain",
                    "description": "light rain",
                    "icon": "10n"
                }
            ],
            "clouds": {
                "all": 78
            },
            "wind": {
                "speed": 3.1,
                "deg": 234,
                "gust": 5.87
            },
            "visibility": 10000,
            "pop": 0.34,
            "rain": {
                "3h": 0.64
            },
            "sys": {
                "pod": "n"
            },
            "dt_txt": "2023-11-29 00:00:00"
        },
        {
            "dt": 1701226800,
            "main": {
                "temp": 278.39,
                "feels_like": 278.39,
                "temp_min": 278.39,
                "temp_max": 278.39,
                "pressure": 1006,
                "sea_level": 1006,
                "grnd_level": 1003,
                "humidity": 87,
                "temp_kf": 0
            },
            "weather": [
                {
                    "id": 500,
                    "main": "Rain",
                    "description": "light rain",
                    "icon": "10n"
                }
            ],
            "clouds": {
                "all": 94
            },
            "wind": {
                "speed": 1.33,
                "deg": 333,
                "gust": 5.1
            },
            "visibility": 10000,
            "pop": 0.54,
            "rain": {
                "3h": 1.13
            },
            "sys": {
                "pod": "n"
            },
            "dt_txt": "2023-11-29 03:00:00"
        },
        {
            "dt": 1701237600,
            "main": {
                "temp": 277.19,
                "feels_like": 275.2,
                "temp_min": 277.19,
                "temp_max": 277.19,
                "pressure": 1006,
                "sea_level": 1006,
                "grnd_level": 1003,
                "humidity": 93,
                "temp_kf": 0
            },
            "weather": [
                {
                    "id": 500,
                    "main": "Rain",
                    "description": "light rain",
                    "icon": "10n"
                }
            ],
            "clouds": {
                "all": 84
            },
            "wind": {
                "speed": 2.19,
                "deg": 39,
                "gust": 3.29
            },
            "visibility": 10000,
            "pop": 0.44,
            "rain": {
                "3h": 0.14
            },
            "sys": {
                "pod": "n"
            },
            "dt_txt": "2023-11-29 06:00:00"
        },
        {
            "dt": 1701248400,
            "main": {
                "temp": 276.55,
                "feels_like": 274.42,
                "temp_min": 276.55,
                "temp_max": 276.55,
                "pressure": 1007,
                "sea_level": 1007,
                "grnd_level": 1003,
                "humidity": 89,
                "temp_kf": 0
            },
            "weather": [
                {
                    "id": 804,
                    "main": "Clouds",
                    "description": "overcast clouds",
                    "icon": "04d"
                }
            ],
            "clouds": {
                "all": 88
            },
            "wind": {
                "speed": 2.22,
                "deg": 53,
                "gust": 4.04
            },
            "visibility": 10000,
            "pop": 0.16,
            "sys": {
                "pod": "d"
            },
            "dt_txt": "2023-11-29 09:00:00"
        },
        {
            "dt": 1701259200,
            "main": {
                "temp": 277.59,
                "feels_like": 275.82,
                "temp_min": 277.59,
                "temp_max": 277.59,
                "pressure": 1007,
                "sea_level": 1007,
                "grnd_level": 1003,
                "humidity": 66,
                "temp_kf": 0
            },
            "weather": [
                {
                    "id": 803,
                    "main": "Clouds",
                    "description": "broken clouds",
                    "icon": "04d"
                }
            ],
            "clouds": {
                "all": 66
            },
            "wind": {
                "speed": 2.04,
                "deg": 45,
                "gust": 2.9
            },
            "visibility": 10000,
            "pop": 0.12,
            "sys": {
                "pod": "d"
            },
            "dt_txt": "2023-11-29 12:00:00"
        },
        {
            "dt": 1701270000,
            "main": {
                "temp": 277.13,
                "feels_like": 274.89,
                "temp_min": 277.13,
                "temp_max": 277.13,
                "pressure": 1006,
                "sea_level": 1006,
                "grnd_level": 1003,
                "humidity": 72,
                "temp_kf": 0
            },
            "weather": [
                {
                    "id": 803,
                    "main": "Clouds",
                    "description": "broken clouds",
                    "icon": "04d"
                }
            ],
            "clouds": {
                "all": 81
            },
            "wind": {
                "speed": 2.45,
                "deg": 50,
                "gust": 4.27
            },
            "visibility": 10000,
            "pop": 0,
            "sys": {
                "pod": "d"
            },
            "dt_txt": "2023-11-29 15:00:00"
        },
        {
            "dt": 1701280800,
            "main": {
                "temp": 275.62,
                "feels_like": 272.71,
                "temp_min": 275.62,
                "temp_max": 275.62,
                "pressure": 1006,
                "sea_level": 1006,
                "grnd_level": 1002,
                "humidity": 80,
                "temp_kf": 0
            },
            "weather": [
                {
                    "id": 803,
                    "main": "Clouds",
                    "description": "broken clouds",
                    "icon": "04n"
                }
            ],
            "clouds": {
                "all": 77
            },
            "wind": {
                "speed": 2.89,
                "deg": 52,
                "gust": 6.39
            },
            "visibility": 10000,
            "pop": 0,
            "sys": {
                "pod": "n"
            },
            "dt_txt": "2023-11-29 18:00:00"
        },
        {
            "dt": 1701291600,
            "main": {
                "temp": 275.27,
                "feels_like": 271.54,
                "temp_min": 275.27,
                "temp_max": 275.27,
                "pressure": 1005,
                "sea_level": 1005,
                "grnd_level": 1002,
                "humidity": 81,
                "temp_kf": 0
            },
            "weather": [
                {
                    "id": 802,
                    "main": "Clouds",
                    "description": "scattered clouds",
                    "icon": "03n"
                }
            ],
            "clouds": {
                "all": 42
            },
            "wind": {
                "speed": 3.89,
                "deg": 65,
                "gust": 9.96
            },
            "visibility": 10000,
            "pop": 0,
            "sys": {
                "pod": "n"
            },
            "dt_txt": "2023-11-29 21:00:00"
        },
        {
            "dt": 1701302400,
            "main": {
                "temp": 274.61,
                "feels_like": 270.89,
                "temp_min": 274.61,
                "temp_max": 274.61,
                "pressure": 1005,
                "sea_level": 1005,
                "grnd_level": 1002,
                "humidity": 79,
                "temp_kf": 0
            },
            "weather": [
                {
                    "id": 803,
                    "main": "Clouds",
                    "description": "broken clouds",
                    "icon": "04n"
                }
            ],
            "clouds": {
                "all": 51
            },
            "wind": {
                "speed": 3.67,
                "deg": 58,
                "gust": 8.95
            },
            "visibility": 10000,
            "pop": 0,
            "sys": {
                "pod": "n"
            },
            "dt_txt": "2023-11-30 00:00:00"
        },
        {
            "dt": 1701313200,
            "main": {
                "temp": 274.33,
                "feels_like": 270.52,
                "temp_min": 274.33,
                "temp_max": 274.33,
                "pressure": 1004,
                "sea_level": 1004,
                "grnd_level": 1001,
                "humidity": 79,
                "temp_kf": 0
            },
            "weather": [
                {
                    "id": 800,
                    "main": "Clear",
                    "description": "clear sky",
                    "icon": "01n"
                }
            ],
            "clouds": {
                "all": 9
            },
            "wind": {
                "speed": 3.71,
                "deg": 56,
                "gust": 8.79
            },
            "visibility": 10000,
            "pop": 0,
            "sys": {
                "pod": "n"
            },
            "dt_txt": "2023-11-30 03:00:00"
        },
        {
            "dt": 1701324000,
            "main": {
                "temp": 274.31,
                "feels_like": 270.19,
                "temp_min": 274.31,
                "temp_max": 274.31,
                "pressure": 1004,
                "sea_level": 1004,
                "grnd_level": 1001,
                "humidity": 80,
                "temp_kf": 0
            },
            "weather": [
                {
                    "id": 800,
                    "main": "Clear",
                    "description": "clear sky",
                    "icon": "01n"
                }
            ],
            "clouds": {
                "all": 8
            },
            "wind": {
                "speed": 4.16,
                "deg": 53,
                "gust": 9.54
            },
            "visibility": 10000,
            "pop": 0,
            "sys": {
                "pod": "n"
            },
            "dt_txt": "2023-11-30 06:00:00"
        },
        {
            "dt": 1701334800,
            "main": {
                "temp": 274.53,
                "feels_like": 270.04,
                "temp_min": 274.53,
                "temp_max": 274.53,
                "pressure": 1005,
                "sea_level": 1005,
                "grnd_level": 1002,
                "humidity": 85,
                "temp_kf": 0
            },
            "weather": [
                {
                    "id": 801,
                    "main": "Clouds",
                    "description": "few clouds",
                    "icon": "02d"
                }
            ],
            "clouds": {
                "all": 13
            },
            "wind": {
                "speed": 4.85,
                "deg": 45,
                "gust": 10.98
            },
            "visibility": 10000,
            "pop": 0,
            "sys": {
                "pod": "d"
            },
            "dt_txt": "2023-11-30 09:00:00"
        },
        {
            "dt": 1701345600,
            "main": {
                "temp": 277.32,
                "feels_like": 273.46,
                "temp_min": 277.32,
                "temp_max": 277.32,
                "pressure": 1005,
                "sea_level": 1005,
                "grnd_level": 1002,
                "humidity": 63,
                "temp_kf": 0
            },
            "weather": [
                {
                    "id": 800,
                    "main": "Clear",
                    "description": "clear sky",
                    "icon": "01d"
                }
            ],
            "clouds": {
                "all": 10
            },
            "wind": {
                "speed": 4.98,
                "deg": 47,
                "gust": 9.64
            },
            "visibility": 10000,
            "pop": 0,
            "sys": {
                "pod": "d"
            },
            "dt_txt": "2023-11-30 12:00:00"
        },
        {
            "dt": 1701356400,
            "main": {
                "temp": 276.92,
                "feels_like": 273.09,
                "temp_min": 276.92,
                "temp_max": 276.92,
                "pressure": 1005,
                "sea_level": 1005,
                "grnd_level": 1002,
                "humidity": 67,
                "temp_kf": 0
            },
            "weather": [
                {
                    "id": 801,
                    "main": "Clouds",
                    "description": "few clouds",
                    "icon": "02d"
                }
            ],
            "clouds": {
                "all": 21
            },
            "wind": {
                "speed": 4.73,
                "deg": 39,
                "gust": 8.68
            },
            "visibility": 10000,
            "pop": 0,
            "sys": {
                "pod": "d"
            },
            "dt_txt": "2023-11-30 15:00:00"
        },
        {
            "dt": 1701367200,
            "main": {
                "temp": 275.41,
                "feels_like": 271.49,
                "temp_min": 275.41,
                "temp_max": 275.41,
                "pressure": 1006,
                "sea_level": 1006,
                "grnd_level": 1003,
                "humidity": 72,
                "temp_kf": 0
            },
            "weather": [
                {
                    "id": 802,
                    "main": "Clouds",
                    "description": "scattered clouds",
                    "icon": "03n"
                }
            ],
            "clouds": {
                "all": 35
            },
            "wind": {
                "speed": 4.24,
                "deg": 33,
                "gust": 9.11
            },
            "visibility": 10000,
            "pop": 0,
            "sys": {
                "pod": "n"
            },
            "dt_txt": "2023-11-30 18:00:00"
        },
        {
            "dt": 1701378000,
            "main": {
                "temp": 274.69,
                "feels_like": 270.28,
                "temp_min": 274.69,
                "temp_max": 274.69,
                "pressure": 1007,
                "sea_level": 1007,
                "grnd_level": 1004,
                "humidity": 76,
                "temp_kf": 0
            },
            "weather": [
                {
                    "id": 803,
                    "main": "Clouds",
                    "description": "broken clouds",
                    "icon": "04n"
                }
            ],
            "clouds": {
                "all": 81
            },
            "wind": {
                "speed": 4.78,
                "deg": 20,
                "gust": 9.85
            },
            "visibility": 10000,
            "pop": 0,
            "sys": {
                "pod": "n"
            },
            "dt_txt": "2023-11-30 21:00:00"
        },
        {
            "dt": 1701388800,
            "main": {
                "temp": 273.92,
                "feels_like": 270.22,
                "temp_min": 273.92,
                "temp_max": 273.92,
                "pressure": 1008,
                "sea_level": 1008,
                "grnd_level": 1005,
                "humidity": 81,
                "temp_kf": 0
            },
            "weather": [
                {
                    "id": 803,
                    "main": "Clouds",
                    "description": "broken clouds",
                    "icon": "04n"
                }
            ],
            "clouds": {
                "all": 52
            },
            "wind": {
                "speed": 3.44,
                "deg": 14,
                "gust": 7.28
            },
            "visibility": 10000,
            "pop": 0,
            "sys": {
                "pod": "n"
            },
            "dt_txt": "2023-12-01 00:00:00"
        },
        {
            "dt": 1701399600,
            "main": {
                "temp": 273.97,
                "feels_like": 270.05,
                "temp_min": 273.97,
                "temp_max": 273.97,
                "pressure": 1009,
                "sea_level": 1009,
                "grnd_level": 1006,
                "humidity": 80,
                "temp_kf": 0
            },
            "weather": [
                {
                    "id": 801,
                    "main": "Clouds",
                    "description": "few clouds",
                    "icon": "02n"
                }
            ],
            "clouds": {
                "all": 14
            },
            "wind": {
                "speed": 3.74,
                "deg": 354,
                "gust": 8.54
            },
            "visibility": 10000,
            "pop": 0,
            "sys": {
                "pod": "n"
            },
            "dt_txt": "2023-12-01 03:00:00"
        },
        {
            "dt": 1701410400,
            "main": {
                "temp": 274.16,
                "feels_like": 270.05,
                "temp_min": 274.16,
                "temp_max": 274.16,
                "pressure": 1010,
                "sea_level": 1010,
                "grnd_level": 1007,
                "humidity": 75,
                "temp_kf": 0
            },
            "weather": [
                {
                    "id": 800,
                    "main": "Clear",
                    "description": "clear sky",
                    "icon": "01n"
                }
            ],
            "clouds": {
                "all": 10
            },
            "wind": {
                "speed": 4.08,
                "deg": 3,
                "gust": 8.72
            },
            "visibility": 10000,
            "pop": 0,
            "sys": {
                "pod": "n"
            },
            "dt_txt": "2023-12-01 06:00:00"
        },
        {
            "dt": 1701421200,
            "main": {
                "temp": 274.11,
                "feels_like": 270.67,
                "temp_min": 274.11,
                "temp_max": 274.11,
                "pressure": 1012,
                "sea_level": 1012,
                "grnd_level": 1008,
                "humidity": 74,
                "temp_kf": 0
            },
            "weather": [
                {
                    "id": 800,
                    "main": "Clear",
                    "description": "clear sky",
                    "icon": "01d"
                }
            ],
            "clouds": {
                "all": 10
            },
            "wind": {
                "speed": 3.16,
                "deg": 359,
                "gust": 6.87
            },
            "visibility": 10000,
            "pop": 0,
            "sys": {
                "pod": "d"
            },
            "dt_txt": "2023-12-01 09:00:00"
        },
        {
            "dt": 1701432000,
            "main": {
                "temp": 276.79,
                "feels_like": 273.7,
                "temp_min": 276.79,
                "temp_max": 276.79,
                "pressure": 1013,
                "sea_level": 1013,
                "grnd_level": 1009,
                "humidity": 65,
                "temp_kf": 0
            },
            "weather": [
                {
                    "id": 800,
                    "main": "Clear",
                    "description": "clear sky",
                    "icon": "01d"
                }
            ],
            "clouds": {
                "all": 10
            },
            "wind": {
                "speed": 3.44,
                "deg": 353,
                "gust": 5.17
            },
            "visibility": 10000,
            "pop": 0,
            "sys": {
                "pod": "d"
            },
            "dt_txt": "2023-12-01 12:00:00"
        },
        {
            "dt": 1701442800,
            "main": {
                "temp": 276.27,
                "feels_like": 273.71,
                "temp_min": 276.27,
                "temp_max": 276.27,
                "pressure": 1013,
                "sea_level": 1013,
                "grnd_level": 1010,
                "humidity": 70,
                "temp_kf": 0
            },
            "weather": [
                {
                    "id": 801,
                    "main": "Clouds",
                    "description": "few clouds",
                    "icon": "02d"
                }
            ],
            "clouds": {
                "all": 14
            },
            "wind": {
                "speed": 2.63,
                "deg": 350,
                "gust": 4.8
            },
            "visibility": 10000,
            "pop": 0,
            "sys": {
                "pod": "d"
            },
            "dt_txt": "2023-12-01 15:00:00"
        },
        {
            "dt": 1701453600,
            "main": {
                "temp": 274.98,
                "feels_like": 273.59,
                "temp_min": 274.98,
                "temp_max": 274.98,
                "pressure": 1014,
                "sea_level": 1014,
                "grnd_level": 1011,
                "humidity": 70,
                "temp_kf": 0
            },
            "weather": [
                {
                    "id": 801,
                    "main": "Clouds",
                    "description": "few clouds",
                    "icon": "02n"
                }
            ],
            "clouds": {
                "all": 14
            },
            "wind": {
                "speed": 1.43,
                "deg": 327,
                "gust": 2.28
            },
            "visibility": 10000,
            "pop": 0,
            "sys": {
                "pod": "n"
            },
            "dt_txt": "2023-12-01 18:00:00"
        },
        {
            "dt": 1701464400,
            "main": {
                "temp": 275,
                "feels_like": 275,
                "temp_min": 275,
                "temp_max": 275,
                "pressure": 1015,
                "sea_level": 1015,
                "grnd_level": 1011,
                "humidity": 72,
                "temp_kf": 0
            },
            "weather": [
                {
                    "id": 803,
                    "main": "Clouds",
                    "description": "broken clouds",
                    "icon": "04n"
                }
            ],
            "clouds": {
                "all": 51
            },
            "wind": {
                "speed": 0.97,
                "deg": 340,
                "gust": 2.47
            },
            "visibility": 10000,
            "pop": 0,
            "sys": {
                "pod": "n"
            },
            "dt_txt": "2023-12-01 21:00:00"
        },
        {
            "dt": 1701475200,
            "main": {
                "temp": 275.39,
                "feels_like": 275.39,
                "temp_min": 275.39,
                "temp_max": 275.39,
                "pressure": 1015,
                "sea_level": 1015,
                "grnd_level": 1012,
                "humidity": 74,
                "temp_kf": 0
            },
            "weather": [
                {
                    "id": 803,
                    "main": "Clouds",
                    "description": "broken clouds",
                    "icon": "04n"
                }
            ],
            "clouds": {
                "all": 71
            },
            "wind": {
                "speed": 0.38,
                "deg": 211,
                "gust": 2.36
            },
            "visibility": 10000,
            "pop": 0.04,
            "sys": {
                "pod": "n"
            },
            "dt_txt": "2023-12-02 00:00:00"
        },
        {
            "dt": 1701486000,
            "main": {
                "temp": 275.23,
                "feels_like": 272.68,
                "temp_min": 275.23,
                "temp_max": 275.23,
                "pressure": 1015,
                "sea_level": 1015,
                "grnd_level": 1012,
                "humidity": 82,
                "temp_kf": 0
            },
            "weather": [
                {
                    "id": 500,
                    "main": "Rain",
                    "description": "light rain",
                    "icon": "10n"
                }
            ],
            "clouds": {
                "all": 63
            },
            "wind": {
                "speed": 2.41,
                "deg": 263,
                "gust": 3.76
            },
            "visibility": 10000,
            "pop": 0.36,
            "rain": {
                "3h": 0.15
            },
            "sys": {
                "pod": "n"
            },
            "dt_txt": "2023-12-02 03:00:00"
        },
        {
            "dt": 1701496800,
            "main": {
                "temp": 275.89,
                "feels_like": 274.25,
                "temp_min": 275.89,
                "temp_max": 275.89,
                "pressure": 1015,
                "sea_level": 1015,
                "grnd_level": 1012,
                "humidity": 81,
                "temp_kf": 0
            },
            "weather": [
                {
                    "id": 500,
                    "main": "Rain",
                    "description": "light rain",
                    "icon": "10n"
                }
            ],
            "clouds": {
                "all": 71
            },
            "wind": {
                "speed": 1.7,
                "deg": 265,
                "gust": 3.61
            },
            "visibility": 10000,
            "pop": 0.36,
            "rain": {
                "3h": 0.25
            },
            "sys": {
                "pod": "n"
            },
            "dt_txt": "2023-12-02 06:00:00"
        },
        {
            "dt": 1701507600,
            "main": {
                "temp": 276.37,
                "feels_like": 274.03,
                "temp_min": 276.37,
                "temp_max": 276.37,
                "pressure": 1015,
                "sea_level": 1015,
                "grnd_level": 1012,
                "humidity": 86,
                "temp_kf": 0
            },
            "weather": [
                {
                    "id": 500,
                    "main": "Rain",
                    "description": "light rain",
                    "icon": "10d"
                }
            ],
            "clouds": {
                "all": 86
            },
            "wind": {
                "speed": 2.41,
                "deg": 244,
                "gust": 3.44
            },
            "visibility": 10000,
            "pop": 0.36,
            "rain": {
                "3h": 0.3
            },
            "sys": {
                "pod": "d"
            },
            "dt_txt": "2023-12-02 09:00:00"
        },
        {
            "dt": 1701518400,
            "main": {
                "temp": 278.64,
                "feels_like": 276.51,
                "temp_min": 278.64,
                "temp_max": 278.64,
                "pressure": 1014,
                "sea_level": 1014,
                "grnd_level": 1011,
                "humidity": 77,
                "temp_kf": 0
            },
            "weather": [
                {
                    "id": 500,
                    "main": "Rain",
                    "description": "light rain",
                    "icon": "10d"
                }
            ],
            "clouds": {
                "all": 93
            },
            "wind": {
                "speed": 2.65,
                "deg": 255,
                "gust": 5.72
            },
            "visibility": 10000,
            "pop": 0.26,
            "rain": {
                "3h": 0.6
            },
            "sys": {
                "pod": "d"
            },
            "dt_txt": "2023-12-02 12:00:00"
        }
    ],
    "city": {
        "id": 2644210,
        "name": "Liverpool",
        "coord": {
            "lat": 53.4072,
            "lon": -2.9917
        },
        "country": "GB",
        "population": 468945,
        "timezone": 0,
        "sunrise": 1701071865,
        "sunset": 1701100894
    }
}